nao_bridge_client/__init__.py
nao_bridge_client/client.py
nao_bridge_client-0.1.5.dist-info/METADATA
nao_bridge_client-0.1.5.dist-info/WHEEL
nao_bridge_client-0.1.5.dist-info/RECORD
